tomldiary/__init__.py
tomldiary/backends/__init__.py
tomldiary/backends/firestore.py
tomldiary/backends/local.py
tomldiary/cli.py
tomldiary/compaction.py
tomldiary/compaction_tools.py
tomldiary/diary.py
tomldiary/extractor_factory.py
tomldiary/loaders.py
tomldiary/logging.py
tomldiary/models.py
tomldiary/pretty_print.py
tomldiary/prompts/compactor_prompt.txt
tomldiary/prompts/extractor_prompt.txt
tomldiary/schema.py
tomldiary/tools.py
tomldiary/utils.py
tomldiary/writer.py
tomldiary-0.6.0.dist-info/licenses/LICENSE
tomldiary-0.6.0.dist-info/WHEEL
tomldiary-0.6.0.dist-info/entry_points.txt
tomldiary-0.6.0.dist-info/METADATA
tomldiary-0.6.0.dist-info/RECORD
