Metadata-Version: 2.4
Name: tomldiary
Version: 0.6.0
Summary: A lightweight TOML-based memory system for AI agents
Keywords: memory,ai,agents,toml,preferences
Author: Jan Siml
Author-email: Jan Siml <49557684+svilupp@users.noreply.github.com>
License-Expression: MIT
License-File: LICENSE
Classifier: Development Status :: 4 - Beta
Classifier: Intended Audience :: Developers
Classifier: Programming Language :: Python :: 3
Classifier: Programming Language :: Python :: 3.11
Classifier: Programming Language :: Python :: 3.12
Classifier: Topic :: Software Development :: Libraries :: Python Modules
Requires-Dist: loguru>=0.7.0
Requires-Dist: pydantic>=2
Requires-Dist: pydantic-ai>=1.0
Requires-Dist: textprompts>=1.0
Requires-Dist: thefuzz>=0.22.1
Requires-Dist: tomli-w
Requires-Dist: google-cloud-firestore>=2.0.0 ; extra == 'firestore'
Requires-Python: >=3.11
Project-URL: Documentation, https://github.com/svilupp/tomldiary/tree/main/docs
Project-URL: Homepage, https://github.com/svilupp/tomldiary
Project-URL: Issues, https://github.com/svilupp/tomldiary/issues
Project-URL: Repository, https://github.com/svilupp/tomldiary
Provides-Extra: firestore
